coveralls_check.py
coveralls_check-1.2.1.dist-info/METADATA
coveralls_check-1.2.1.dist-info/RECORD
coveralls_check-1.2.1.dist-info/WHEEL
coveralls_check-1.2.1.dist-info/entry_points.txt
coveralls_check-1.2.1.dist-info/top_level.txt
