Metadata-Version: 2.1
Name: coveralls-check
Version: 1.2.1
Summary: Check coverage at https://coveralls.io
Home-page: https://github.com/cjw296/coverage-check
Author: Chris Withers
Author-email: chris@withers.org
License: MIT
Platform: UNKNOWN
Classifier: Development Status :: 5 - Production/Stable
Classifier: Intended Audience :: Developers
Classifier: License :: OSI Approved :: MIT License
Classifier: Programming Language :: Python :: 2
Classifier: Programming Language :: Python :: 2.7
Classifier: Programming Language :: Python :: 3
Classifier: Programming Language :: Python :: 3.6
Provides-Extra: test
Provides-Extra: build
Requires-Dist: requests
Requires-Dist: backoff
Provides-Extra: build
Requires-Dist: setuptools-git; extra == 'build'
Requires-Dist: twine; extra == 'build'
Requires-Dist: wheel; extra == 'build'
Provides-Extra: test
Requires-Dist: pytest; extra == 'test'
Requires-Dist: testfixtures; extra == 'test'
Requires-Dist: responses; extra == 'test'
Requires-Dist: coveralls; extra == 'test'
Requires-Dist: mock; extra == 'test'
